{"cameraMode":{"drawMode":0,"name":"Shaded","section":"Shading Mode"},"sceneLighting":true,"audioPlay":false,"sceneViewState":{"m_AlwaysRefresh":false,"showFog":true,"showSkybox":true,"showFlares":true,"showImageEffects":true,"showParticleSystems":true,"showVisualEffectGraphs":true,"m_FxEnabled":true},"in2DMode":false,"pivot":{"x":-6.183616638183594,"y":-0.906219482421875,"z":3.7680177688598635},"rotation":{"x":-0.3700081706047058,"y":0.4410410225391388,"z":-0.206254243850708,"w":-0.7912748456001282},"size":9.008133888244629,"orthographic":false}